README.rst
casserole.py
setup.py
casserole.egg-info/PKG-INFO
casserole.egg-info/SOURCES.txt
casserole.egg-info/dependency_links.txt
casserole.egg-info/top_level.txt