Metadata-Version: 1.1
Name: casserole
Version: 0.1.0
Summary: simplify reading configuration values from multiple sources
Home-page: http://github.com/coleifer/casserole/
Author: Charles Leifer
Author-email: coleifer@gmail.com
License: UNKNOWN
Platform: UNKNOWN
Classifier: Development Status :: 5 - Production/Stable
Classifier: Intended Audience :: Developers
Classifier: License :: OSI Approved :: MIT License
Classifier: Operating System :: OS Independent
Classifier: Programming Language :: Python
